calcasa/api/__init__.py
calcasa/api/api_client.py
calcasa/api/configuration.py
calcasa/api/exceptions.py
calcasa/api/model_utils.py
calcasa/api/rest.py
calcasa/api/api/__init__.py
calcasa/api/api/adressen_api.py
calcasa/api/api/bestemmingsplannen_api.py
calcasa/api/api/bodem_api.py
calcasa/api/api/buurt_api.py
calcasa/api/api/callbacks_api.py
calcasa/api/api/configuratie_api.py
calcasa/api/api/facturen_api.py
calcasa/api/api/fotos_api.py
calcasa/api/api/funderingen_api.py
calcasa/api/api/geldverstrekkers_api.py
calcasa/api/api/rapporten_api.py
calcasa/api/api/waarderingen_api.py
calcasa/api/apis/__init__.py
calcasa/api/model/__init__.py
calcasa/api/model/aanvraagdoel.py
calcasa/api/model/adres.py
calcasa/api/model/adres_info.py
calcasa/api/model/bestemmingsdata.py
calcasa/api/model/bodem_status_type.py
calcasa/api/model/bodemdata.py
calcasa/api/model/business_rules_code.py
calcasa/api/model/business_rules_problem_details.py
calcasa/api/model/callback.py
calcasa/api/model/callback_inschrijving.py
calcasa/api/model/cbs_indeling.py
calcasa/api/model/deel_waardering_webhook_payload.py
calcasa/api/model/energielabel.py
calcasa/api/model/energielabel_data.py
calcasa/api/model/factuur.py
calcasa/api/model/foto.py
calcasa/api/model/fundering_data_bron.py
calcasa/api/model/fundering_herstel_type.py
calcasa/api/model/fundering_risico.py
calcasa/api/model/fundering_risico_label.py
calcasa/api/model/fundering_soort_bron.py
calcasa/api/model/fundering_type.py
calcasa/api/model/fundering_typering.py
calcasa/api/model/funderingdata.py
calcasa/api/model/gebiedsdata.py
calcasa/api/model/geldverstrekker.py
calcasa/api/model/invalid_argument_problem_details.py
calcasa/api/model/json_patch_document.py
calcasa/api/model/klantwaarde_type.py
calcasa/api/model/kwartaal.py
calcasa/api/model/modeldata.py
calcasa/api/model/not_found_problem_details.py
calcasa/api/model/notitie.py
calcasa/api/model/notities.py
calcasa/api/model/objectdata.py
calcasa/api/model/omgevingsdata.py
calcasa_api-1.3.1.dist-info/LICENSE
calcasa_api-1.3.1.dist-info/METADATA
calcasa_api-1.3.1.dist-info/WHEEL
calcasa_api-1.3.1.dist-info/top_level.txt
calcasa_api-1.3.1.dist-info/RECORD
