Metadata-Version: 2.1
Name: calcasa-api
Version: 1.3.1
Summary: Calcasa Public API v1
Home-page: https://github.com/calcasa/api-python
Author: Calcasa B.V.
Author-email: info@calcasa.nl
License: Apache-2.0
Keywords: OpenAPI,OpenAPI-Generator,Calcasa Public API v1
Classifier: Programming Language :: Python :: 3 :: Only
Classifier: License :: OSI Approved :: Apache Software License
Requires-Python: >=3.6
License-File: LICENSE
Requires-Dist: urllib3 (>=1.25.3)
Requires-Dist: python-dateutil
